setup.cfg
setup.py
nexus_stats/__init__.py
nexus_stats/api.py
nexus_stats/exceptions.py
nexus_stats/profile.py
nexus_stats.py.egg-info/PKG-INFO
nexus_stats.py.egg-info/SOURCES.txt
nexus_stats.py.egg-info/dependency_links.txt
nexus_stats.py.egg-info/requires.txt
nexus_stats.py.egg-info/top_level.txt